csgomenumaker/__init__.py
csgomenumaker/__main__.py
csgomenumaker/main.py
csgomenumaker/Command/Color.py
csgomenumaker/Command/Command.py
csgomenumaker/Command/Compound.py
csgomenumaker/Command/Dialog.py
csgomenumaker/Command/Echo.py
csgomenumaker/Command/File.py
csgomenumaker/Command/Folder.py
csgomenumaker/Command/Indirect.py
csgomenumaker/Command/Null.py
csgomenumaker/Command/Placeholder.py
csgomenumaker/Command/Primitive.py
csgomenumaker/Command/Realias.py
csgomenumaker/Command/Root.py
csgomenumaker/Command/__init__.py
csgomenumaker/Command/NavState/Horz.py
csgomenumaker/Command/NavState/NavState.py
csgomenumaker/Command/NavState/Vert.py
csgomenumaker/Command/NavState/VertFolder.py
csgomenumaker/Command/NavState/__init__.py
csgomenumaker/Component/Bots.py
csgomenumaker/Component/Cheats.py
csgomenumaker/Component/ConfigLoader.py
csgomenumaker/Component/ConfigType.py
csgomenumaker/Component/ConfigTypeMapping.py
csgomenumaker/Component/Debug.py
csgomenumaker/Component/Demo.py
csgomenumaker/Component/Game.py
csgomenumaker/Component/Generic.py
csgomenumaker/Component/Sound.py
csgomenumaker/Component/__init__.py
csgomenumaker/Menu/Bar.py
csgomenumaker/Menu/Choice.py
csgomenumaker/Menu/ChoiceVar.py
csgomenumaker/Menu/ChoiceVarBinary.py
csgomenumaker/Menu/Fireable.py
csgomenumaker/Menu/FireableCmd.py
csgomenumaker/Menu/Folder.py
csgomenumaker/Menu/Menu.py
csgomenumaker/Menu/Message.py
csgomenumaker/Menu/PresetChooser.py
csgomenumaker/Menu/Root.py
csgomenumaker/Menu/SlotChooser.py
csgomenumaker/Menu/__init__.py
csgomenumaker/Misc/Math.py
csgomenumaker/Misc/Text.py
csgomenumaker/Misc/__init__.py
csgo_menu_maker-0.1.2.dist-info/LICENSE
csgo_menu_maker-0.1.2.dist-info/METADATA
csgo_menu_maker-0.1.2.dist-info/WHEEL
csgo_menu_maker-0.1.2.dist-info/top_level.txt
csgo_menu_maker-0.1.2.dist-info/RECORD
